jvmanager/__init__.py
jvmanager/cli.py
jvmanager/group.py
jvmanager/commands/__init__.py
jvmanager/commands/launch.py
jvmanager/manager/client/favicon.ico
jvmanager/manager/client/index.html
jvmanager/manager/client/assets/ActionIcon-55kNUHHC.js
jvmanager/manager/client/assets/Avatar-DueFptlw.js
jvmanager/manager/client/assets/Badge-C-Zq__Qu.js
jvmanager/manager/client/assets/Button-kXQ3kFES.js
jvmanager/manager/client/assets/Card-Dow6iKi0.js
jvmanager/manager/client/assets/CloseButton-Dy-wbEsU.js
jvmanager/manager/client/assets/DirectionProvider-DuCsFlA9.js
jvmanager/manager/client/assets/Divider-DNtoRLi1.js
jvmanager/manager/client/assets/FocusTrap-DSZiEh9q.js
jvmanager/manager/client/assets/Group-3SoFkW_U.js
jvmanager/manager/client/assets/IconArrowLeft-CZ1KUR1o.js
jvmanager/manager/client/assets/Input-Dk8j5b2Q.js
jvmanager/manager/client/assets/InputsGroupFieldset-C5T_ipTq.js
jvmanager/manager/client/assets/Loader-B9JD8HZZ.js
jvmanager/manager/client/assets/Modal-DI6cVWVp.js
jvmanager/manager/client/assets/OptionalPortal-BQJEy_xn.js
jvmanager/manager/client/assets/PackageCard-BU9c_QO4.js
jvmanager/manager/client/assets/PackageCard-CBL6piyC.css
jvmanager/manager/client/assets/Paper-C4kvkNN2.js
jvmanager/manager/client/assets/PasswordInput-1a3PblwM.js
jvmanager/manager/client/assets/Popover-Bqo8g6N_.js
jvmanager/manager/client/assets/ScrollArea-DZ4wk0Ci.js
jvmanager/manager/client/assets/SimpleGrid-B3GKyrsx.js
jvmanager/manager/client/assets/Stack-CyWGn-AO.js
jvmanager/manager/client/assets/Text-BRX5JXq7.js
jvmanager/manager/client/assets/Title-CmbW-mDV.js
jvmanager/manager/client/assets/UserButton-BVGfPNpG.js
jvmanager/manager/client/assets/UserButton-DFVFx_YX.css
jvmanager/manager/client/assets/action-details-rXxTIBdv.js
jvmanager/manager/client/assets/actions-BLZrsZJW.css
jvmanager/manager/client/assets/actions-Degbxgax.js
jvmanager/manager/client/assets/add-action-lKd9ENl_.js
jvmanager/manager/client/assets/api-tgDzxHzW.js
jvmanager-2.1.25.dist-info/licenses/LICENSE
jvmanager-2.1.25.dist-info/METADATA
jvmanager-2.1.25.dist-info/WHEEL
jvmanager-2.1.25.dist-info/entry_points.txt
jvmanager-2.1.25.dist-info/top_level.txt
jvmanager-2.1.25.dist-info/RECORD
