Metadata-Version: 2.4
Name: jvmanager
Version: 2.1.25
License-File: LICENSE
Requires-Dist: click
Requires-Dist: fastapi
Requires-Dist: uvicorn
Requires-Dist: python-multipart
Dynamic: description
Dynamic: license-file
Dynamic: requires-dist
